bside/__init__.py
bside/dataset.py
bside/dmd.py
bside/dynamics.py
bside/models.py
bside/ssm.py
bside/subspace_encoder.py
bside/filtering/__init__.py
bside/filtering/distributions.py
bside/filtering/filters.py
bside/filtering/functional.py
bside/filtering/plotting.py
bside-0.0.1.dist-info/licenses/LICENSE
bside-0.0.1.dist-info/METADATA
bside-0.0.1.dist-info/WHEEL
bside-0.0.1.dist-info/top_level.txt
bside-0.0.1.dist-info/RECORD
