Metadata-Version: 2.4
Name: bside
Version: 0.0.1
Summary: Bayesian system identification toolbox
Author-email: Nicholas Galioto <ngalioto@umich.edu>
License: MIT
Project-URL: Homepage, https://github.com/ngalioto/bside
Keywords: Bayesian inference,system identification,dynamical systems,dynamics,filtering,DMD,model uncertainty,stochastic dynamics,probabilistic inference
Classifier: Intended Audience :: Science/Research
Classifier: License :: OSI Approved :: MIT License
Classifier: Natural Language :: English
Classifier: Operating System :: OS Independent
Classifier: Programming Language :: Python :: 3
Classifier: Topic :: Scientific/Engineering :: Mathematics
Requires-Python: >=3.8
License-File: LICENSE
Requires-Dist: torch
Requires-Dist: numpy
Requires-Dist: scipy
Dynamic: license-file
